l3py/__init__.py
l3py/filter.py
l3py/gravityfield.py
l3py/grid.py
l3py/io.py
l3py/kernel.py
l3py/utilities.py
l3py/data/ddk_normals.npz
l3py/data/loadLoveNumbers_Gegout97.txt
l3py-0.2.dist-info/LICENSE
l3py-0.2.dist-info/METADATA
l3py-0.2.dist-info/WHEEL
l3py-0.2.dist-info/top_level.txt
l3py-0.2.dist-info/RECORD
