Metadata-Version: 2.1
Name: l3py
Version: 0.2
Summary: A python package to convert potential coefficients to gridded mass anomalies
Home-page: UNKNOWN
Author: Andreas Kvas
Author-email: UNKNOWN
License: UNKNOWN
Platform: UNKNOWN
Classifier: Programming Language :: Python :: 3
Classifier: License :: OSI Approved :: MIT License
Classifier: Operating System :: OS Independent
Requires-Dist: numpy
Requires-Dist: netcdf4
Requires-Dist: numpydoc
